isomut2py/__init__.py
isomut2py/bayesian.py
isomut2py/compare.py
isomut2py/examples.py
isomut2py/format.py
isomut2py/io.py
isomut2py/mutationcalling.py
isomut2py/ploidyestimation.py
isomut2py/plot.py
isomut2py/postprocess.py
isomut2py/process.py
isomut2py/C/PEprep.c
isomut2py/C/checkPileup.c
isomut2py/C/fisher.c
isomut2py/C/isomut2.c
isomut2py/C/isomut2_lib.c
isomut2py/C/isomut2_lib.h
isomut2py/alexandrovSignatures/sigProfiler_DBS_signatures.csv
isomut2py/alexandrovSignatures/sigProfiler_ID_signatures.csv
isomut2py/alexandrovSignatures/sigProfiler_SBS_signatures_2018_03_28.csv
isomut2py-2.0.8.dist-info/LICENSE
isomut2py-2.0.8.dist-info/METADATA
isomut2py-2.0.8.dist-info/WHEEL
isomut2py-2.0.8.dist-info/top_level.txt
isomut2py-2.0.8.dist-info/RECORD
